current_temp_api/__init__.py
current_temp_api/api.py
current_temp_api/base.py
python_api_current_temperature-0.0.1.dist-info/LICENSE
python_api_current_temperature-0.0.1.dist-info/METADATA
python_api_current_temperature-0.0.1.dist-info/WHEEL
python_api_current_temperature-0.0.1.dist-info/top_level.txt
python_api_current_temperature-0.0.1.dist-info/RECORD
