Metadata-Version: 2.1
Name: python_api_current_temperature
Version: 0.0.1
Summary: A simple client module to get temperature from different service providers over api
Home-page: https://github.com/AmirhosseinAmirzadeh/Python-Current-Temp-Api
Author: AmirHossein Amirzadeh
Author-email: Amirzadeh@live.com
Project-URL: Author, https://eamirzadeh.ir
Classifier: Programming Language :: Python :: 3
Classifier: License :: OSI Approved :: MIT License
Classifier: Operating System :: OS Independent
Requires-Python: >=3.6
License-File: LICENSE
Requires-Dist: requests
